azqueuemanager/__init__.py
azqueuemanager/extension.py
azqueuemanager/queue.py
azqueuemanager-0.0.6.dist-info/METADATA
azqueuemanager-0.0.6.dist-info/WHEEL
azqueuemanager-0.0.6.dist-info/top_level.txt
azqueuemanager-0.0.6.dist-info/RECORD
