Metadata-Version: 2.1
Name: azqueuemanager
Version: 0.0.6
Summary: Storage Queue Input-Output Manager for Azure Storage Queue
License: MIT
Keywords: azqueuemanager
Classifier: Programming Language :: Python :: 3
Requires-Python: >=3.10
Requires-Dist: azure-storage-queue
Requires-Dist: azure-functions
